<?xml version="1.0" encoding="UTF-8" ?>
<!DOCTYPE mapper PUBLIC "-//mybatis.org//DTD Mapper 3.0//EN" "http://mybatis.org/dtd/mybatis-3-mapper.dtd" >
<mapper namespace="org.mskcc.cbio.importer.cvr.crdb.rdbms.dao.cbioint.CrdbImpactSurveyMapper" >
  <resultMap id="BaseResultMap" type="org.mskcc.cbio.importer.cvr.crdb.rdbms.model.cbioint.CrdbImpactSurvey" >
    <!--
      WARNING - @mbggenerated
      This element is automatically generated by MyBatis Generator, do not modify.
      This element was generated on Sun Feb 22 09:49:16 EST 2015.
    -->
    <result column="DMP_ID" property="DMP_ID" jdbcType="VARCHAR" />
    <result column="QS_DATE" property="QS_DATE" jdbcType="TIMESTAMP" />
    <result column="ADJ_TXT" property="ADJ_TXT" jdbcType="VARCHAR" />
    <result column="NOSYSTXT" property="NOSYSTXT" jdbcType="VARCHAR" />
    <result column="PRIOR_RX" property="PRIOR_RX" jdbcType="VARCHAR" />
    <result column="BRAINMET" property="BRAINMET" jdbcType="VARCHAR" />
    <result column="ECOG" property="ECOG" jdbcType="VARCHAR" />
  </resultMap>
  <sql id="Example_Where_Clause" >
    <!--
      WARNING - @mbggenerated
      This element is automatically generated by MyBatis Generator, do not modify.
      This element was generated on Sun Feb 22 09:49:16 EST 2015.
    -->
    <where >
      <foreach collection="oredCriteria" item="criteria" separator="or" >
        <if test="criteria.valid" >
          <trim prefix="(" suffix=")" prefixOverrides="and" >
            <foreach collection="criteria.criteria" item="criterion" >
              <choose >
                <when test="criterion.noValue" >
                  and ${criterion.condition}
                </when>
                <when test="criterion.singleValue" >
                  and ${criterion.condition} #{criterion.value}
                </when>
                <when test="criterion.betweenValue" >
                  and ${criterion.condition} #{criterion.value} and #{criterion.secondValue}
                </when>
                <when test="criterion.listValue" >
                  and ${criterion.condition}
                  <foreach collection="criterion.value" item="listItem" open="(" close=")" separator="," >
                    #{listItem}
                  </foreach>
                </when>
              </choose>
            </foreach>
          </trim>
        </if>
      </foreach>
    </where>
  </sql>
  <sql id="Update_By_Example_Where_Clause" >
    <!--
      WARNING - @mbggenerated
      This element is automatically generated by MyBatis Generator, do not modify.
      This element was generated on Sun Feb 22 09:49:16 EST 2015.
    -->
    <where >
      <foreach collection="example.oredCriteria" item="criteria" separator="or" >
        <if test="criteria.valid" >
          <trim prefix="(" suffix=")" prefixOverrides="and" >
            <foreach collection="criteria.criteria" item="criterion" >
              <choose >
                <when test="criterion.noValue" >
                  and ${criterion.condition}
                </when>
                <when test="criterion.singleValue" >
                  and ${criterion.condition} #{criterion.value}
                </when>
                <when test="criterion.betweenValue" >
                  and ${criterion.condition} #{criterion.value} and #{criterion.secondValue}
                </when>
                <when test="criterion.listValue" >
                  and ${criterion.condition}
                  <foreach collection="criterion.value" item="listItem" open="(" close=")" separator="," >
                    #{listItem}
                  </foreach>
                </when>
              </choose>
            </foreach>
          </trim>
        </if>
      </foreach>
    </where>
  </sql>
  <sql id="Base_Column_List" >
    <!--
      WARNING - @mbggenerated
      This element is automatically generated by MyBatis Generator, do not modify.
      This element was generated on Sun Feb 22 09:49:16 EST 2015.
    -->
    DMP_ID, QS_DATE, ADJ_TXT, NOSYSTXT, PRIOR_RX, BRAINMET, ECOG
  </sql>
  <select id="selectByExample" resultMap="BaseResultMap" parameterType="org.mskcc.cbio.importer.cvr.crdb.rdbms.model.cbioint.CrdbImpactSurveyExample" >
    <!--
      WARNING - @mbggenerated
      This element is automatically generated by MyBatis Generator, do not modify.
      This element was generated on Sun Feb 22 09:49:16 EST 2015.
    -->
    select
    <if test="distinct" >
      distinct
    </if>
    <include refid="Base_Column_List" />
    from CBIOINT.V_IMPACT_SURVEY_12_245
    <if test="_parameter != null" >
      <include refid="Example_Where_Clause" />
    </if>
    <if test="orderByClause != null" >
      order by ${orderByClause}
    </if>
  </select>
  <delete id="deleteByExample" parameterType="org.mskcc.cbio.importer.cvr.crdb.rdbms.model.cbioint.CrdbImpactSurveyExample" >
    <!--
      WARNING - @mbggenerated
      This element is automatically generated by MyBatis Generator, do not modify.
      This element was generated on Sun Feb 22 09:49:16 EST 2015.
    -->
    delete from CBIOINT.V_IMPACT_SURVEY_12_245
    <if test="_parameter != null" >
      <include refid="Example_Where_Clause" />
    </if>
  </delete>
  <insert id="insert" parameterType="org.mskcc.cbio.importer.cvr.crdb.rdbms.model.cbioint.CrdbImpactSurvey" >
    <!--
      WARNING - @mbggenerated
      This element is automatically generated by MyBatis Generator, do not modify.
      This element was generated on Sun Feb 22 09:49:16 EST 2015.
    -->
    insert into CBIOINT.V_IMPACT_SURVEY_12_245 (DMP_ID, QS_DATE, ADJ_TXT, 
      NOSYSTXT, PRIOR_RX, BRAINMET, 
      ECOG)
    values (#{DMP_ID,jdbcType=VARCHAR}, #{QS_DATE,jdbcType=TIMESTAMP}, #{ADJ_TXT,jdbcType=VARCHAR}, 
      #{NOSYSTXT,jdbcType=VARCHAR}, #{PRIOR_RX,jdbcType=VARCHAR}, #{BRAINMET,jdbcType=VARCHAR}, 
      #{ECOG,jdbcType=VARCHAR})
  </insert>
  <insert id="insertSelective" parameterType="org.mskcc.cbio.importer.cvr.crdb.rdbms.model.cbioint.CrdbImpactSurvey" >
    <!--
      WARNING - @mbggenerated
      This element is automatically generated by MyBatis Generator, do not modify.
      This element was generated on Sun Feb 22 09:49:16 EST 2015.
    -->
    insert into CBIOINT.V_IMPACT_SURVEY_12_245
    <trim prefix="(" suffix=")" suffixOverrides="," >
      <if test="DMP_ID != null" >
        DMP_ID,
      </if>
      <if test="QS_DATE != null" >
        QS_DATE,
      </if>
      <if test="ADJ_TXT != null" >
        ADJ_TXT,
      </if>
      <if test="NOSYSTXT != null" >
        NOSYSTXT,
      </if>
      <if test="PRIOR_RX != null" >
        PRIOR_RX,
      </if>
      <if test="BRAINMET != null" >
        BRAINMET,
      </if>
      <if test="ECOG != null" >
        ECOG,
      </if>
    </trim>
    <trim prefix="values (" suffix=")" suffixOverrides="," >
      <if test="DMP_ID != null" >
        #{DMP_ID,jdbcType=VARCHAR},
      </if>
      <if test="QS_DATE != null" >
        #{QS_DATE,jdbcType=TIMESTAMP},
      </if>
      <if test="ADJ_TXT != null" >
        #{ADJ_TXT,jdbcType=VARCHAR},
      </if>
      <if test="NOSYSTXT != null" >
        #{NOSYSTXT,jdbcType=VARCHAR},
      </if>
      <if test="PRIOR_RX != null" >
        #{PRIOR_RX,jdbcType=VARCHAR},
      </if>
      <if test="BRAINMET != null" >
        #{BRAINMET,jdbcType=VARCHAR},
      </if>
      <if test="ECOG != null" >
        #{ECOG,jdbcType=VARCHAR},
      </if>
    </trim>
  </insert>
  <select id="countByExample" parameterType="org.mskcc.cbio.importer.cvr.crdb.rdbms.model.cbioint.CrdbImpactSurveyExample" resultType="java.lang.Integer" >
    <!--
      WARNING - @mbggenerated
      This element is automatically generated by MyBatis Generator, do not modify.
      This element was generated on Sun Feb 22 09:49:16 EST 2015.
    -->
    select count(*) from CBIOINT.V_IMPACT_SURVEY_12_245
    <if test="_parameter != null" >
      <include refid="Example_Where_Clause" />
    </if>
  </select>
  <update id="updateByExampleSelective" parameterType="map" >
    <!--
      WARNING - @mbggenerated
      This element is automatically generated by MyBatis Generator, do not modify.
      This element was generated on Sun Feb 22 09:49:16 EST 2015.
    -->
    update CBIOINT.V_IMPACT_SURVEY_12_245
    <set >
      <if test="record.DMP_ID != null" >
        DMP_ID = #{record.DMP_ID,jdbcType=VARCHAR},
      </if>
      <if test="record.QS_DATE != null" >
        QS_DATE = #{record.QS_DATE,jdbcType=TIMESTAMP},
      </if>
      <if test="record.ADJ_TXT != null" >
        ADJ_TXT = #{record.ADJ_TXT,jdbcType=VARCHAR},
      </if>
      <if test="record.NOSYSTXT != null" >
        NOSYSTXT = #{record.NOSYSTXT,jdbcType=VARCHAR},
      </if>
      <if test="record.PRIOR_RX != null" >
        PRIOR_RX = #{record.PRIOR_RX,jdbcType=VARCHAR},
      </if>
      <if test="record.BRAINMET != null" >
        BRAINMET = #{record.BRAINMET,jdbcType=VARCHAR},
      </if>
      <if test="record.ECOG != null" >
        ECOG = #{record.ECOG,jdbcType=VARCHAR},
      </if>
    </set>
    <if test="_parameter != null" >
      <include refid="Update_By_Example_Where_Clause" />
    </if>
  </update>
  <update id="updateByExample" parameterType="map" >
    <!--
      WARNING - @mbggenerated
      This element is automatically generated by MyBatis Generator, do not modify.
      This element was generated on Sun Feb 22 09:49:16 EST 2015.
    -->
    update CBIOINT.V_IMPACT_SURVEY_12_245
    set DMP_ID = #{record.DMP_ID,jdbcType=VARCHAR},
      QS_DATE = #{record.QS_DATE,jdbcType=TIMESTAMP},
      ADJ_TXT = #{record.ADJ_TXT,jdbcType=VARCHAR},
      NOSYSTXT = #{record.NOSYSTXT,jdbcType=VARCHAR},
      PRIOR_RX = #{record.PRIOR_RX,jdbcType=VARCHAR},
      BRAINMET = #{record.BRAINMET,jdbcType=VARCHAR},
      ECOG = #{record.ECOG,jdbcType=VARCHAR}
    <if test="_parameter != null" >
      <include refid="Update_By_Example_Where_Clause" />
    </if>
  </update>
</mapper>